mugisync/__init__.py
mugisync/__main__.py
mugisync-0.0.15.dist-info/LICENSE
mugisync-0.0.15.dist-info/METADATA
mugisync-0.0.15.dist-info/WHEEL
mugisync-0.0.15.dist-info/entry_points.txt
mugisync-0.0.15.dist-info/top_level.txt
mugisync-0.0.15.dist-info/RECORD
