Metadata-Version: 2.2
Name: mugisync
Version: 0.0.15
Summary: Continously syncronizes local directory with another local or shared directory (poor person's syncthing) or remote directory over ssh (poor person's one-way sshfs)
Home-page: https://github.com/mugiseyebrows/mugi-sync
Author: Stanislav Doronin
Author-email: mugisbrows@gmail.com
License-File: LICENSE
Requires-Dist: eventloop
Requires-Dist: colorama
Requires-Dist: paramiko
Dynamic: author
Dynamic: author-email
Dynamic: description
Dynamic: home-page
Dynamic: requires-dist
Dynamic: summary
